{
    "Bouchene": {
        "visits": [
            {
                "date": "2025-04-02",
                "arrived_at": "2025-04-02 21:46:39",
                "called_at": "2025-04-02 21:46:51",
                "checkout_at": "2025-04-02 21:46:54"
            }
        ]
    },
    "bouchene": {
        "visits": [
            {
                "date": "2025-04-02",
                "arrived_at": "2025-04-02 21:47:05",
                "called_at": "2025-04-02 21:47:31",
                "checkout_at": "2025-04-02 21:47:36"
            },
            {
                "date": "2025-04-02",
                "arrived_at": "2025-04-02 22:02:21",
                "called_at": "2025-04-02 22:02:35",
                "checkout_at": "2025-04-02 22:02:49"
            },
            {
                "date": "2025-04-02",
                "arrived_at": "2025-04-02 22:05:14"
            },
            {
                "date": "2025-04-02",
                "arrived_at": "2025-04-02 22:06:23"
            },
            {
                "date": "2025-04-02",
                "arrived_at": "2025-04-02 22:08:50",
                "called_at": "2025-04-02 22:08:57"
            },
            {
                "date": "2025-04-02",
                "arrived_at": "2025-04-02 22:22:17"
            }
        ]
    },
    "bakha": {
        "visits": [
            {
                "date": "2025-04-02",
                "arrived_at": "2025-04-02 21:47:08",
                "called_at": "2025-04-02 21:47:43",
                "checkout_at": "2025-04-02 21:47:44"
            },
            {
                "date": "2025-04-02",
                "arrived_at": "2025-04-02 22:05:17"
            },
            {
                "date": "2025-04-02",
                "arrived_at": "2025-04-02 22:06:18",
                "called_at": "2025-04-02 22:06:26"
            },
            {
                "date": "2025-04-02",
                "arrived_at": "2025-04-02 22:08:55"
            }
        ]
    },
    "galboze": {
        "visits": [
            {
                "date": "2025-04-02",
                "arrived_at": "2025-04-02 21:47:14"
            }
        ]
    },
    "hdhdh": {
        "visits": [
            {
                "date": "2025-04-02",
                "arrived_at": "2025-04-02 21:47:27"
            }
        ]
    },
    "bouhs": {
        "visits": [
            {
                "date": "2025-04-02",
                "arrived_at": "2025-04-02 22:02:27"
            }
        ]
    },
    "bsnsnmsm": {
        "visits": [
            {
                "date": "2025-04-02",
                "arrived_at": "2025-04-02 22:02:33"
            }
        ]
    },
    "hhd": {
        "visits": [
            {
                "date": "2025-04-02",
                "arrived_at": "2025-04-02 22:04:54",
                "called_at": "2025-04-02 22:05:00",
                "checkout_at": "2025-04-02 22:05:28"
            }
        ]
    },
    "nn": {
        "visits": [
            {
                "date": "2025-04-02",
                "arrived_at": "2025-04-02 22:04:56",
                "called_at": "2025-04-02 22:05:40"
            }
        ]
    },
    "bicc": {
        "visits": [
            {
                "date": "2025-04-02",
                "arrived_at": "2025-04-02 22:10:52",
                "called_at": "2025-04-02 22:10:56",
                "checkout_at": "2025-04-02 22:11:00"
            }
        ]
    },
    "hhsh": {
        "visits": [
            {
                "date": "2025-04-02",
                "arrived_at": "2025-04-02 22:10:55"
            }
        ]
    },
    "hand": {
        "visits": [
            {
                "date": "2025-04-02",
                "arrived_at": "2025-04-02 22:22:21"
            }
        ]
    },
    "nnn": {
        "visits": [
            {
                "date": "2025-04-02",
                "arrived_at": "2025-04-02 22:49:01",
                "called_at": "2025-04-02 22:49:04",
                "checkout_at": "2025-04-02 22:49:06"
            },
            {
                "date": "2025-04-02",
                "arrived_at": "2025-04-02 22:51:25",
                "called_at": "2025-04-02 22:51:26",
                "checkout_at": "2025-04-02 22:51:28"
            }
        ]
    },
    "vv": {
        "visits": [
            {
                "date": "2025-04-02",
                "arrived_at": "2025-04-02 22:53:37",
                "called_at": "2025-04-02 22:53:43",
                "checkout_at": "2025-04-02 22:53:47"
            }
        ]
    },
    "hhhhh": {
        "visits": [
            {
                "date": "2025-04-02",
                "arrived_at": "2025-04-02 22:53:42"
            }
        ]
    },
    "GGG": {
        "visits": [
            {
                "date": "2025-04-02",
                "arrived_at": "2025-04-02 23:04:23",
                "called_at": "2025-04-02 23:04:31",
                "checkout_at": "2025-04-02 23:04:42",
                "total_paid": 0
            }
        ]
    },
    "DDD": {
        "visits": [
            {
                "date": "2025-04-02",
                "arrived_at": "2025-04-02 23:04:26",
                "called_at": "2025-04-02 23:04:56",
                "checkout_at": "2025-04-02 23:05:07",
                "total_paid": 0
            }
        ]
    },
    "NNN": {
        "visits": [
            {
                "date": "2025-04-02",
                "arrived_at": "2025-04-02 23:08:35",
                "called_at": "2025-04-02 23:08:38",
                "checkout_at": "2025-04-02 23:08:42",
                "total_paid": 0
            }
        ]
    },
    "KJK": {
        "visits": [
            {
                "date": "2025-04-02",
                "arrived_at": "2025-04-02 23:11:25",
                "called_at": "2025-04-02 23:11:33",
                "checkout_at": "2025-04-02 23:11:57",
                "services": [],
                "total_paid": 0
            }
        ]
    },
    "MNNMNNM": {
        "visits": [
            {
                "date": "2025-04-02",
                "arrived_at": "2025-04-02 23:11:28"
            }
        ]
    },
    "NMNMDNMNM": {
        "visits": [
            {
                "date": "2025-04-02",
                "arrived_at": "2025-04-02 23:13:53",
                "called_at": "2025-04-02 23:14:03",
                "checkout_at": "2025-04-02 23:14:22",
                "services": [
                    "Consultation",
                    "Radiographie",
                    "gg"
                ],
                "total_paid": 4330
            }
        ]
    },
    "NMCNMCN": {
        "visits": [
            {
                "date": "2025-04-02",
                "arrived_at": "2025-04-02 23:13:56"
            }
        ]
    },
    "CNNMCN": {
        "visits": [
            {
                "date": "2025-04-02",
                "arrived_at": "2025-04-02 23:13:59"
            }
        ]
    },
    "NMNDMNM": {
        "visits": [
            {
                "date": "2025-04-02",
                "arrived_at": "2025-04-02 23:15:00"
            }
        ]
    },
    "BOUC": {
        "visits": [
            {
                "date": "2025-04-02",
                "arrived_at": "2025-04-02 23:18:06",
                "called_at": "2025-04-02 23:18:22",
                "checkout_at": "2025-04-02 23:18:38",
                "services": [
                    "Consultation",
                    "EFR"
                ],
                "total_paid": 2500
            }
        ]
    },
    "GSFSF": {
        "visits": [
            {
                "date": "2025-04-02",
                "arrived_at": "2025-04-02 23:18:10"
            }
        ]
    },
    "DHDHDHJ": {
        "visits": [
            {
                "date": "2025-04-02",
                "arrived_at": "2025-04-02 23:18:13"
            }
        ]
    },
    "NXNXMNM": {
        "visits": [
            {
                "date": "2025-04-02",
                "arrived_at": "2025-04-02 23:18:15"
            }
        ]
    },
    "ncjcjc": {
        "visits": [
            {
                "date": "2025-04-02",
                "arrived_at": "2025-04-02 23:27:02"
            },
            {
                "date": "2025-04-02",
                "arrived_at": "2025-04-02 23:27:05"
            },
            {
                "date": "2025-04-02",
                "arrived_at": "2025-04-02 23:27:05"
            },
            {
                "date": "2025-04-02",
                "arrived_at": "2025-04-02 23:27:05"
            },
            {
                "date": "2025-04-02",
                "arrived_at": "2025-04-02 23:27:06"
            },
            {
                "date": "2025-04-02",
                "arrived_at": "2025-04-02 23:27:06"
            },
            {
                "date": "2025-04-02",
                "arrived_at": "2025-04-02 23:27:06"
            },
            {
                "date": "2025-04-02",
                "arrived_at": "2025-04-02 23:28:29"
            }
        ]
    },
    "nnmd": {
        "visits": [
            {
                "date": "2025-04-02",
                "arrived_at": "2025-04-02 23:30:33"
            }
        ]
    },
    "nmdnm": {
        "visits": [
            {
                "date": "2025-04-02",
                "arrived_at": "2025-04-02 23:31:48",
                "called_at": "2025-04-02 23:32:11",
                "checkout_at": "2025-04-02 23:32:26",
                "services": [
                    "Consultation",
                    "EFR",
                    "gg"
                ],
                "total_paid": 4830
            }
        ]
    },
    "nmnmnc": {
        "visits": [
            {
                "date": "2025-04-02",
                "arrived_at": "2025-04-02 23:31:58"
            }
        ]
    },
    "c c cnnmc": {
        "visits": [
            {
                "date": "2025-04-02",
                "arrived_at": "2025-04-02 23:32:04"
            }
        ]
    },
    "nxnmnmx": {
        "visits": [
            {
                "date": "2025-04-02",
                "arrived_at": "2025-04-02 23:36:22",
                "called_at": "2025-04-02 23:37:01",
                "checkout_at": "2025-04-02 23:37:16",
                "services": [
                    "Analyse de sang",
                    "Radiographie",
                    "EFR"
                ],
                "total_paid": 4500
            }
        ]
    },
    "mnmn": {
        "visits": [
            {
                "date": "2025-04-02",
                "arrived_at": "2025-04-02 23:36:30"
            }
        ]
    },
    "cnmnmc": {
        "visits": [
            {
                "date": "2025-04-02",
                "arrived_at": "2025-04-02 23:36:34"
            }
        ]
    },
    "mcnmcnm": {
        "visits": [
            {
                "date": "2025-04-02",
                "arrived_at": "2025-04-02 23:36:38"
            }
        ]
    }
}